slurm_to_wandb/__init__.py
slurm_to_wandb/main.py
slurm_to_wandb/sacct_to_df.py
slurm_to_wandb-0.1.2.dist-info/LICENSE
slurm_to_wandb-0.1.2.dist-info/METADATA
slurm_to_wandb-0.1.2.dist-info/WHEEL
slurm_to_wandb-0.1.2.dist-info/entry_points.txt
slurm_to_wandb-0.1.2.dist-info/top_level.txt
slurm_to_wandb-0.1.2.dist-info/RECORD
