Metadata-Version: 2.1
Name: slurm-to-wandb
Version: 0.1.2
Summary: Uploads SLURM job information to WandB for better monitoring.
Home-page: https://github.com/dunnkers/slurm-to-wandb
Author: Jeroen Overschie
License: MIT
Platform: UNKNOWN
Requires-Dist: pandas (>=1.2)
Requires-Dist: wandb (>=0.10)
Requires-Dist: numpy (>=1.19)
Requires-Dist: humanfriendly (==9.1)
